tetris.cpython-311-x86_64-linux-gnu.so
tetris_c-0.1.dist-info/METADATA
tetris_c-0.1.dist-info/top_level.txt
tetris_c-0.1.dist-info/WHEEL
tetris_c-0.1.dist-info/RECORD
tetris_c.libs/libSDL2-2-d214786e.0.so.0.10.0
