Metadata-Version: 2.1
Name: tetris_c
Version: 0.1
Summary: Modern tetris python library, implemented in C++ for speed. Requires SDL2 to render, if you dont want rendering choose the tetris_c_nore version
Home-page: https://github.com/TheFantasticWarrior/tetris-cpy
Author: TFW
Author-email: TFW <tfwplssub@gmail.com>
License: MIT License
Project-URL: Homepage, https://github.com/TheFantasticWarrior/tetris-cpy
Project-URL: Issues, https://github.com/TheFantasticWarrior/tetris-cpy/issues
Classifier: Programming Language :: Python :: 3
Classifier: License :: OSI Approved :: MIT License
Classifier: Operating System :: POSIX :: Linux
Classifier: Operating System :: Microsoft :: Windows
Classifier: Environment :: MacOS X
Classifier: Development Status :: 4 - Beta
Classifier: Topic :: Games/Entertainment :: Puzzle Games
Classifier: Topic :: Games/Entertainment
Classifier: Topic :: Scientific/Engineering :: Artificial Intelligence
Classifier: Topic :: Software Development :: Libraries :: Python Modules
Requires-Dist: numpy
